lwdb/__init__.py
lwdb-0.0.dist-info/METADATA
lwdb-0.0.dist-info/WHEEL
lwdb-0.0.dist-info/top_level.txt
lwdb-0.0.dist-info/RECORD
