Metadata-Version: 2.1
Name: lwdb
Version: 0.0
Summary: LWDB
Home-page: https://www.github.com/rickwierenga/lwdb/
Author: Rick Wierenga
Author-email: rick_wierenga@icloud.com
